cp_tools/__init__.py
cp_tools/helpers.py
cp_tools/tester.py
cp_tools/get_tests/__init__.py
cp_tools/get_tests/atcoder.py
cp_tools/get_tests/codeforces.py
cp_tools-0.1.1.dist-info/LICENSE
cp_tools-0.1.1.dist-info/METADATA
cp_tools-0.1.1.dist-info/WHEEL
cp_tools-0.1.1.dist-info/top_level.txt
cp_tools-0.1.1.dist-info/RECORD
